{"pages":["Montserrat-VariableFontwght.png"],"chars":[{"id":87,"index":331,"char":"W","width":46,"height":33,"xoffset":0,"yoffset":14,"xadvance":45,"chnl":15,"x":0,"y":0,"page":0},{"id":47,"index":2243,"char":"/","width":19,"height":44,"xoffset":-3,"yoffset":8,"xadvance":13,"chnl":15,"x":0,"y":34,"page":0},{"id":92,"index":2244,"char":"\\","width":19,"height":44,"xoffset":-3,"yoffset":8,"xadvance":13,"chnl":15,"x":0,"y":79,"page":0},{"id":36,"index":2350,"char":"$","width":24,"height":43,"xoffset":0,"yoffset":9,"xadvance":25,"chnl":15,"x":0,"y":124,"page":0},{"id":123,"index":2270,"char":"{","width":13,"height":43,"xoffset":1,"yoffset":12,"xadvance":13,"chnl":15,"x":20,"y":34,"page":0},{"id":125,"index":2271,"char":"}","width":13,"height":43,"xoffset":-1,"yoffset":12,"xadvance":13,"chnl":15,"x":20,"y":78,"page":0},{"id":91,"index":2272,"char":"[","width":9,"height":43,"xoffset":4,"yoffset":12,"xadvance":12,"chnl":15,"x":0,"y":168,"page":0},{"id":93,"index":2273,"char":"]","width":9,"height":43,"xoffset":-1,"yoffset":12,"xadvance":12,"chnl":15,"x":0,"y":212,"page":0},{"id":124,"index":2330,"char":"|","width":5,"height":43,"xoffset":4,"yoffset":12,"xadvance":12,"chnl":15,"x":0,"y":256,"page":0},{"id":40,"index":2268,"char":"(","width":9,"height":43,"xoffset":3,"yoffset":12,"xadvance":13,"chnl":15,"x":0,"y":300,"page":0},{"id":41,"index":2269,"char":")","width":9,"height":43,"xoffset":0,"yoffset":12,"xadvance":13,"chnl":15,"x":6,"y":256,"page":0},{"id":106,"index":741,"char":"j","width":14,"height":42,"xoffset":-6,"yoffset":13,"xadvance":11,"chnl":15,"x":10,"y":168,"page":0},{"id":64,"index":2320,"char":"@","width":42,"height":42,"xoffset":0,"yoffset":13,"xadvance":43,"chnl":15,"x":10,"y":211,"page":0},{"id":199,"index":49,"char":"Ç","width":29,"height":42,"xoffset":0,"yoffset":13,"xadvance":29,"chnl":15,"x":25,"y":122,"page":0},{"id":212,"index":210,"char":"Ô","width":34,"height":41,"xoffset":0,"yoffset":7,"xadvance":35,"chnl":15,"x":25,"y":165,"page":0},{"id":219,"index":297,"char":"Û","width":27,"height":41,"xoffset":3,"yoffset":7,"xadvance":33,"chnl":15,"x":34,"y":34,"page":0},{"id":192,"index":22,"char":"À","width":32,"height":40,"xoffset":-2,"yoffset":7,"xadvance":29,"chnl":15,"x":34,"y":76,"page":0},{"id":194,"index":10,"char":"Â","width":32,"height":40,"xoffset":-2,"yoffset":7,"xadvance":29,"chnl":15,"x":55,"y":117,"page":0},{"id":201,"index":73,"char":"É","width":24,"height":40,"xoffset":4,"yoffset":7,"xadvance":28,"chnl":15,"x":62,"y":0,"page":0},{"id":200,"index":89,"char":"È","width":24,"height":40,"xoffset":4,"yoffset":7,"xadvance":28,"chnl":15,"x":67,"y":41,"page":0},{"id":202,"index":78,"char":"Ê","width":24,"height":40,"xoffset":4,"yoffset":7,"xadvance":28,"chnl":15,"x":87,"y":0,"page":0},{"id":206,"index":140,"char":"Î","width":16,"height":40,"xoffset":-2,"yoffset":7,"xadvance":12,"chnl":15,"x":0,"y":344,"page":0},{"id":214,"index":217,"char":"Ö","width":34,"height":40,"xoffset":0,"yoffset":8,"xadvance":35,"chnl":15,"x":10,"y":300,"page":0},{"id":220,"index":300,"char":"Ü","width":27,"height":40,"xoffset":3,"yoffset":8,"xadvance":33,"chnl":15,"x":16,"y":254,"page":0},{"id":81,"index":252,"char":"Q","width":35,"height":39,"xoffset":0,"yoffset":13,"xadvance":35,"chnl":15,"x":44,"y":254,"page":0},{"id":109,"index":774,"char":"m","width":39,"height":26,"xoffset":3,"yoffset":21,"xadvance":45,"chnl":15,"x":67,"y":82,"page":0},{"id":203,"index":86,"char":"Ë","width":24,"height":39,"xoffset":4,"yoffset":8,"xadvance":28,"chnl":15,"x":92,"y":41,"page":0},{"id":207,"index":142,"char":"Ï","width":13,"height":39,"xoffset":-1,"yoffset":8,"xadvance":12,"chnl":15,"x":112,"y":0,"page":0},{"id":119,"index":925,"char":"w","width":38,"height":26,"xoffset":-1,"yoffset":21,"xadvance":35,"chnl":15,"x":53,"y":207,"page":0},{"id":167,"index":2323,"char":"§","width":21,"height":38,"xoffset":-1,"yoffset":13,"xadvance":20,"chnl":15,"x":60,"y":158,"page":0},{"id":98,"index":617,"char":"b","width":25,"height":35,"xoffset":3,"yoffset":12,"xadvance":28,"chnl":15,"x":82,"y":158,"page":0},{"id":100,"index":638,"char":"d","width":25,"height":35,"xoffset":0,"yoffset":12,"xadvance":28,"chnl":15,"x":88,"y":109,"page":0},{"id":102,"index":689,"char":"f","width":18,"height":35,"xoffset":-1,"yoffset":12,"xadvance":13,"chnl":15,"x":0,"y":385,"page":0},{"id":104,"index":706,"char":"h","width":23,"height":35,"xoffset":3,"yoffset":12,"xadvance":28,"chnl":15,"x":17,"y":341,"page":0},{"id":107,"index":748,"char":"k","width":22,"height":35,"xoffset":3,"yoffset":12,"xadvance":24,"chnl":15,"x":0,"y":421,"page":0},{"id":108,"index":757,"char":"l","width":5,"height":35,"xoffset":3,"yoffset":12,"xadvance":11,"chnl":15,"x":19,"y":377,"page":0},{"id":231,"index":630,"char":"ç","width":22,"height":35,"xoffset":0,"yoffset":21,"xadvance":23,"chnl":15,"x":0,"y":457,"page":0},{"id":67,"index":45,"char":"C","width":29,"height":34,"xoffset":0,"yoffset":13,"xadvance":29,"chnl":15,"x":23,"y":413,"page":0},{"id":71,"index":110,"char":"G","width":29,"height":34,"xoffset":0,"yoffset":13,"xadvance":33,"chnl":15,"x":25,"y":377,"page":0},{"id":74,"index":155,"char":"J","width":19,"height":34,"xoffset":-2,"yoffset":14,"xadvance":20,"chnl":15,"x":41,"y":341,"page":0},{"id":79,"index":204,"char":"O","width":34,"height":34,"xoffset":0,"yoffset":13,"xadvance":35,"chnl":15,"x":45,"y":294,"page":0},{"id":83,"index":266,"char":"S","width":24,"height":34,"xoffset":0,"yoffset":13,"xadvance":25,"chnl":15,"x":23,"y":448,"page":0},{"id":85,"index":292,"char":"U","width":27,"height":34,"xoffset":3,"yoffset":14,"xadvance":33,"chnl":15,"x":48,"y":448,"page":0},{"id":103,"index":691,"char":"g","width":25,"height":34,"xoffset":0,"yoffset":21,"xadvance":28,"chnl":15,"x":53,"y":412,"page":0},{"id":105,"index":719,"char":"i","width":6,"height":34,"xoffset":2,"yoffset":13,"xadvance":11,"chnl":15,"x":55,"y":376,"page":0},{"id":112,"index":837,"char":"p","width":25,"height":34,"xoffset":3,"yoffset":21,"xadvance":28,"chnl":15,"x":61,"y":329,"page":0},{"id":113,"index":843,"char":"q","width":25,"height":34,"xoffset":0,"yoffset":21,"xadvance":28,"chnl":15,"x":62,"y":364,"page":0},{"id":121,"index":937,"char":"y","width":26,"height":34,"xoffset":-3,"yoffset":21,"xadvance":21,"chnl":15,"x":76,"y":447,"page":0},{"id":48,"index":2099,"char":"0","width":26,"height":34,"xoffset":0,"yoffset":13,"xadvance":27,"chnl":15,"x":79,"y":399,"page":0},{"id":50,"index":2101,"char":"2","width":24,"height":34,"xoffset":-1,"yoffset":13,"xadvance":23,"chnl":15,"x":103,"y":434,"page":0},{"id":51,"index":2102,"char":"3","width":24,"height":34,"xoffset":-1,"yoffset":14,"xadvance":23,"chnl":15,"x":103,"y":469,"page":0},{"id":53,"index":2104,"char":"5","width":24,"height":34,"xoffset":-1,"yoffset":14,"xadvance":23,"chnl":15,"x":80,"y":234,"page":0},{"id":54,"index":2105,"char":"6","width":25,"height":34,"xoffset":0,"yoffset":13,"xadvance":25,"chnl":15,"x":92,"y":194,"page":0},{"id":56,"index":2107,"char":"8","width":26,"height":34,"xoffset":0,"yoffset":13,"xadvance":26,"chnl":15,"x":108,"y":145,"page":0},{"id":57,"index":2108,"char":"9","width":25,"height":34,"xoffset":0,"yoffset":13,"xadvance":25,"chnl":15,"x":80,"y":269,"page":0},{"id":63,"index":2237,"char":"?","width":23,"height":34,"xoffset":-1,"yoffset":13,"xadvance":23,"chnl":15,"x":105,"y":229,"page":0},{"id":33,"index":2235,"char":"!","width":6,"height":34,"xoffset":2,"yoffset":14,"xadvance":10,"chnl":15,"x":118,"y":180,"page":0},{"id":163,"index":2365,"char":"£","width":28,"height":34,"xoffset":-1,"yoffset":13,"xadvance":26,"chnl":15,"x":125,"y":180,"page":0},{"id":38,"index":2321,"char":"&","width":28,"height":34,"xoffset":0,"yoffset":13,"xadvance":27,"chnl":15,"x":87,"y":304,"page":0},{"id":37,"index":2399,"char":"%","width":33,"height":34,"xoffset":0,"yoffset":13,"xadvance":34,"chnl":15,"x":106,"y":264,"page":0},{"id":181,"index":2397,"char":"µ","width":22,"height":34,"xoffset":3,"yoffset":21,"xadvance":28,"chnl":15,"x":129,"y":215,"page":0},{"id":224,"index":601,"char":"à","width":21,"height":34,"xoffset":1,"yoffset":13,"xadvance":24,"chnl":15,"x":88,"y":339,"page":0},{"id":226,"index":589,"char":"â","width":21,"height":34,"xoffset":1,"yoffset":13,"xadvance":24,"chnl":15,"x":106,"y":374,"page":0},{"id":233,"index":654,"char":"é","width":24,"height":34,"xoffset":0,"yoffset":13,"xadvance":25,"chnl":15,"x":110,"y":339,"page":0},{"id":232,"index":670,"char":"è","width":24,"height":34,"xoffset":0,"yoffset":13,"xadvance":25,"chnl":15,"x":116,"y":299,"page":0},{"id":234,"index":659,"char":"ê","width":24,"height":34,"xoffset":0,"yoffset":13,"xadvance":25,"chnl":15,"x":140,"y":250,"page":0},{"id":238,"index":724,"char":"î","width":13,"height":34,"xoffset":-1,"yoffset":13,"xadvance":11,"chnl":15,"x":152,"y":215,"page":0},{"id":244,"index":800,"char":"ô","width":25,"height":34,"xoffset":0,"yoffset":13,"xadvance":26,"chnl":15,"x":114,"y":81,"page":0},{"id":249,"index":902,"char":"ù","width":22,"height":34,"xoffset":3,"yoffset":13,"xadvance":28,"chnl":15,"x":117,"y":40,"page":0},{"id":251,"index":892,"char":"û","width":22,"height":34,"xoffset":3,"yoffset":13,"xadvance":28,"chnl":15,"x":126,"y":0,"page":0},{"id":8364,"index":2352,"char":"€","width":34,"height":34,"xoffset":-1,"yoffset":13,"xadvance":33,"chnl":15,"x":135,"y":116,"page":0},{"id":65,"index":1,"char":"A","width":32,"height":33,"xoffset":-2,"yoffset":14,"xadvance":29,"chnl":15,"x":154,"y":151,"page":0},{"id":66,"index":37,"char":"B","width":27,"height":33,"xoffset":4,"yoffset":14,"xadvance":31,"chnl":15,"x":140,"y":35,"page":0},{"id":68,"index":56,"char":"D","width":31,"height":33,"xoffset":4,"yoffset":14,"xadvance":35,"chnl":15,"x":149,"y":0,"page":0},{"id":69,"index":72,"char":"E","width":24,"height":33,"xoffset":4,"yoffset":14,"xadvance":28,"chnl":15,"x":140,"y":69,"page":0},{"id":70,"index":107,"char":"F","width":23,"height":33,"xoffset":4,"yoffset":14,"xadvance":26,"chnl":15,"x":165,"y":69,"page":0},{"id":72,"index":122,"char":"H","width":27,"height":33,"xoffset":4,"yoffset":14,"xadvance":34,"chnl":15,"x":168,"y":34,"page":0},{"id":73,"index":134,"char":"I","width":5,"height":33,"xoffset":4,"yoffset":14,"xadvance":12,"chnl":15,"x":47,"y":0,"page":0},{"id":75,"index":159,"char":"K","width":27,"height":33,"xoffset":4,"yoffset":14,"xadvance":29,"chnl":15,"x":181,"y":0,"page":0},{"id":76,"index":167,"char":"L","width":22,"height":33,"xoffset":4,"yoffset":14,"xadvance":24,"chnl":15,"x":170,"y":103,"page":0},{"id":77,"index":183,"char":"M","width":33,"height":33,"xoffset":4,"yoffset":14,"xadvance":40,"chnl":15,"x":189,"y":68,"page":0},{"id":78,"index":189,"char":"N","width":27,"height":33,"xoffset":4,"yoffset":14,"xadvance":34,"chnl":15,"x":196,"y":34,"page":0},{"id":80,"index":246,"char":"P","width":26,"height":33,"xoffset":4,"yoffset":14,"xadvance":30,"chnl":15,"x":209,"y":0,"page":0},{"id":82,"index":254,"char":"R","width":26,"height":33,"xoffset":4,"yoffset":14,"xadvance":30,"chnl":15,"x":128,"y":374,"page":0},{"id":84,"index":279,"char":"T","width":27,"height":33,"xoffset":-2,"yoffset":14,"xadvance":23,"chnl":15,"x":135,"y":334,"page":0},{"id":86,"index":325,"char":"V","width":31,"height":33,"xoffset":-2,"yoffset":14,"xadvance":28,"chnl":15,"x":141,"y":285,"page":0},{"id":88,"index":339,"char":"X","width":28,"height":33,"xoffset":-1,"yoffset":14,"xadvance":26,"chnl":15,"x":165,"y":250,"page":0},{"id":89,"index":342,"char":"Y","width":29,"height":33,"xoffset":-2,"yoffset":14,"xadvance":26,"chnl":15,"x":166,"y":185,"page":0},{"id":90,"index":355,"char":"Z","width":27,"height":33,"xoffset":0,"yoffset":14,"xadvance":27,"chnl":15,"x":187,"y":137,"page":0},{"id":49,"index":2100,"char":"1","width":12,"height":33,"xoffset":-2,"yoffset":14,"xadvance":14,"chnl":15,"x":193,"y":102,"page":0},{"id":52,"index":2103,"char":"4","width":28,"height":33,"xoffset":0,"yoffset":14,"xadvance":27,"chnl":15,"x":206,"y":102,"page":0},{"id":55,"index":2106,"char":"7","width":24,"height":33,"xoffset":0,"yoffset":14,"xadvance":24,"chnl":15,"x":223,"y":68,"page":0},{"id":35,"index":2242,"char":"#","width":30,"height":33,"xoffset":-1,"yoffset":14,"xadvance":29,"chnl":15,"x":224,"y":34,"page":0},{"id":235,"index":667,"char":"ë","width":24,"height":33,"xoffset":0,"yoffset":14,"xadvance":25,"chnl":15,"x":236,"y":0,"page":0},{"id":239,"index":726,"char":"ï","width":11,"height":33,"xoffset":0,"yoffset":14,"xadvance":11,"chnl":15,"x":128,"y":408,"page":0},{"id":246,"index":807,"char":"ö","width":25,"height":33,"xoffset":0,"yoffset":14,"xadvance":26,"chnl":15,"x":128,"y":442,"page":0},{"id":252,"index":895,"char":"ü","width":22,"height":33,"xoffset":3,"yoffset":14,"xadvance":28,"chnl":15,"x":140,"y":408,"page":0},{"id":59,"index":2233,"char":";","width":6,"height":32,"xoffset":1,"yoffset":21,"xadvance":8,"chnl":15,"x":53,"y":0,"page":0},{"id":248,"index":829,"char":"ø","width":25,"height":32,"xoffset":0,"yoffset":18,"xadvance":26,"chnl":15,"x":128,"y":476,"page":0},{"id":116,"index":873,"char":"t","width":18,"height":31,"xoffset":-1,"yoffset":17,"xadvance":16,"chnl":15,"x":155,"y":368,"page":0},{"id":97,"index":580,"char":"a","width":21,"height":26,"xoffset":1,"yoffset":21,"xadvance":24,"chnl":15,"x":23,"y":483,"page":0},{"id":99,"index":626,"char":"c","width":22,"height":26,"xoffset":0,"yoffset":21,"xadvance":23,"chnl":15,"x":45,"y":483,"page":0},{"id":101,"index":653,"char":"e","width":24,"height":26,"xoffset":0,"yoffset":21,"xadvance":25,"chnl":15,"x":76,"y":482,"page":0},{"id":110,"index":780,"char":"n","width":23,"height":26,"xoffset":3,"yoffset":21,"xadvance":28,"chnl":15,"x":166,"y":219,"page":0},{"id":111,"index":795,"char":"o","width":25,"height":26,"xoffset":0,"yoffset":21,"xadvance":26,"chnl":15,"x":190,"y":219,"page":0},{"id":114,"index":845,"char":"r","width":13,"height":26,"xoffset":3,"yoffset":21,"xadvance":16,"chnl":15,"x":114,"y":116,"page":0},{"id":115,"index":859,"char":"s","width":21,"height":26,"xoffset":-1,"yoffset":21,"xadvance":19,"chnl":15,"x":196,"y":171,"page":0},{"id":117,"index":887,"char":"u","width":22,"height":26,"xoffset":3,"yoffset":21,"xadvance":28,"chnl":15,"x":215,"y":136,"page":0},{"id":118,"index":920,"char":"v","width":25,"height":26,"xoffset":-2,"yoffset":21,"xadvance":21,"chnl":15,"x":235,"y":102,"page":0},{"id":120,"index":934,"char":"x","width":23,"height":26,"xoffset":-1,"yoffset":21,"xadvance":21,"chnl":15,"x":248,"y":68,"page":0},{"id":122,"index":951,"char":"z","width":21,"height":26,"xoffset":0,"yoffset":21,"xadvance":21,"chnl":15,"x":255,"y":34,"page":0},{"id":58,"index":2232,"char":":","width":6,"height":26,"xoffset":1,"yoffset":21,"xadvance":8,"chnl":15,"x":107,"y":81,"page":0},{"id":126,"index":2386,"char":"~","width":22,"height":9,"xoffset":1,"yoffset":26,"xadvance":24,"chnl":15,"x":60,"y":197,"page":0},{"id":178,"index":2201,"char":"²","width":18,"height":22,"xoffset":0,"yoffset":12,"xadvance":18,"chnl":15,"x":135,"y":151,"page":0},{"id":43,"index":2374,"char":"+","width":21,"height":21,"xoffset":1,"yoffset":20,"xadvance":24,"chnl":15,"x":106,"y":409,"page":0},{"id":61,"index":2378,"char":"=","width":21,"height":14,"xoffset":1,"yoffset":23,"xadvance":24,"chnl":15,"x":141,"y":319,"page":0},{"id":42,"index":2241,"char":"*","width":17,"height":18,"xoffset":-1,"yoffset":12,"xadvance":15,"chnl":15,"x":88,"y":374,"page":0},{"id":176,"index":2327,"char":"°","width":17,"height":17,"xoffset":1,"yoffset":13,"xadvance":18,"chnl":15,"x":53,"y":234,"page":0},{"id":45,"index":2258,"char":"-","width":15,"height":5,"xoffset":1,"yoffset":31,"xadvance":16,"chnl":15,"x":45,"y":329,"page":0},{"id":39,"index":2291,"char":"'","width":5,"height":15,"xoffset":1,"yoffset":14,"xadvance":8,"chnl":15,"x":80,"y":304,"page":0},{"id":44,"index":2231,"char":",","width":6,"height":12,"xoffset":1,"yoffset":41,"xadvance":8,"chnl":15,"x":62,"y":399,"page":0},{"id":96,"index":2605,"char":"`","width":12,"height":9,"xoffset":5,"yoffset":13,"xadvance":25,"chnl":15,"x":79,"y":434,"page":0},{"id":46,"index":2230,"char":".","width":6,"height":6,"xoffset":1,"yoffset":41,"xadvance":8,"chnl":15,"x":128,"y":116,"page":0},{"id":32,"index":2219,"char":" ","width":0,"height":0,"xoffset":-2,"yoffset":43,"xadvance":11,"chnl":15,"x":44,"y":294,"page":0}],"info":{"face":"Montserrat-VariableFontwght","size":42,"bold":0,"italic":0,"charset":["A","B","C","D","E","F","G","H","I","J","K","L","M","N","O","P","Q","R","S","T","U","V","W","X","Y","Z","a","b","c","d","e","f","g","h","i","j","k","l","m","n","o","p","q","r","s","t","u","v","w","x","y","z","0","1","2","3","4","5","6","7","8","9",".","?","!","/",":",";",",","*","§","£","$","ø","@","+","°","-","~","#","&","²","'","{","}","[","]","|","`","\\","(",")","=","%","µ"," ","à","â","é","è","ë","ê","ï","î","ö","ô","ù","ü","û","À","Â","É","È","Ë","Ê","Ï","Î","Ö","Ô","Ü","Û","ç","Ç","€"],"unicode":1,"stretchH":100,"smooth":1,"aa":1,"padding":[2,2,2,2],"spacing":[0,0]},"common":{"lineHeight":51,"base":43,"scaleW":512,"scaleH":512,"pages":1,"packed":0,"alphaChnl":0,"redChnl":0,"greenChnl":0,"blueChnl":0},"distanceField":{"fieldType":"msdf","distanceRange":4},"kernings":[]}